fidi_common_libraries/__init__.py
fidi_common_libraries/aws/__init__.py
fidi_common_libraries/aws/common_aws.py
fidi_common_libraries/config/__init__.py
fidi_common_libraries/config/parametros.py
fidi_common_libraries/config/README.md
fidi_common_libraries/constants/__init__.py
fidi_common_libraries/constants/README.md
fidi_common_libraries/constants/status.py
fidi_common_libraries/data/__init__.py
fidi_common_libraries/data/db_data.py
fidi_common_libraries/data/README.md
fidi_common_libraries/logging_framework/__init__.py
fidi_common_libraries/logging_framework/core/__init__.py
fidi_common_libraries/logging_framework/core/base_logger.py
fidi_common_libraries/logging_framework/core/generic_logger.py
fidi_common_libraries/logging_framework/core/logger_factory.py
fidi_common_libraries/logging_framework/specialized/__init__.py
fidi_common_libraries/logging_framework/specialized/api_logger.py
fidi_common_libraries/logging_framework/specialized/automation_logger.py
fidi_common_libraries/logging_framework/specialized/database_logger.py
fidi_common_libraries/logging_framework/specialized/security_logger.py
fidi_common_libraries/logging_framework/specialized/web_logger.py
fidi_common_libraries/ui/__init__.py
fidi_common_libraries/ui/config/__init__.py
fidi_common_libraries/ui/config/ui_config.py
fidi_common_libraries/ui/core/__init__.py
fidi_common_libraries/ui/core/application.py
fidi_common_libraries/ui/core/element_finder.py
fidi_common_libraries/ui/core/image_finder.py
fidi_common_libraries/ui/core/interactions.py
fidi_common_libraries/ui/core/position_finder.py
fidi_common_libraries/ui/core/rm_adapt_navigator.py
fidi_common_libraries/ui/core/rm_close.py
fidi_common_libraries/ui/core/rm_dual_connect.py
fidi_common_libraries/ui/core/rm_login_env_selector.py
fidi_common_libraries/ui/core/rm_navigator.py
fidi_common_libraries/ui/core/rm_planilha_net.py
fidi_common_libraries/ui/core/rm_progress_monitor.py
fidi_common_libraries/ui/core/rm_single_connect.py
fidi_common_libraries-1.3.20.dist-info/LICENSE
fidi_common_libraries-1.3.20.dist-info/METADATA
fidi_common_libraries-1.3.20.dist-info/WHEEL
fidi_common_libraries-1.3.20.dist-info/RECORD
