Metadata-Version: 2.3
Name: fidi-common-libraries
Version: 1.3.20
Summary: Bibliotecas compartilhadas entre os projetos da FIDI
License: MIT
Keywords: fidi,aws,utils,database,logger
Author: Vander Loto
Author-email: vander.loto@datametria.io
Requires-Python: >=3.11,<4.0
Classifier: Development Status :: 5 - Production/Stable
Classifier: License :: OSI Approved :: MIT License
Classifier: Programming Language :: Python :: 3
Classifier: Programming Language :: Python :: 3.11
Classifier: Programming Language :: Python :: 3.12
Classifier: Programming Language :: Python :: 3.13
Requires-Dist: boto3 (>=1.34.0,<2.0.0)
Requires-Dist: botocore (>=1.34.0,<2.0.0)
Requires-Dist: numpy (>=2.3.1,<3.0.0)
Requires-Dist: opencv-python (>=4.8.0,<5.0.0)
Requires-Dist: oracledb (>=3.2.0,<4.0.0)
Requires-Dist: pandas (>=2.3.1,<3.0.0)
Requires-Dist: pillow (>=10.0.0,<11.0.0)
Requires-Dist: psutil (>=7.0.0,<8.0.0)
Requires-Dist: psycopg2 (>=2.9.10,<3.0.0)
Requires-Dist: pygetwindow (>=0.0.9,<0.0.10)
Requires-Dist: pynput (>=1.8.1,<2.0.0)
Requires-Dist: pyodbc (>=5.2.0,<6.0.0)
Requires-Dist: python-dotenv (>=1.0.0,<2.0.0)
Requires-Dist: pywinauto (>=0.6.8,<0.7.0)
Requires-Dist: pyyaml (>=6.0.2,<7.0.0)
Requires-Dist: sqlalchemy (>=2.0.41,<3.0.0)
Project-URL: Changelog, https://github.com/exolyze/FIDI-common-libraries/releases
Project-URL: Documentation, https://github.com/exolyze/FIDI-common-libraries/README.md
Project-URL: Homepage, https://github.com/exolyze/FIDI-common-libraries
Project-URL: Repository, https://github.com/exolyze/FIDI-common-libraries
